[
  {
    "id": "c_f595_a",
    "title": "Albo Pretorio del Comune di Montereale",
    "description": "*non ufficiale* RSS feed dell'Albo Pretorio di Montereale",
    "administration": "Comune di Montereale",
    "ipa_code": "c_f595",
    "istat_code": "66056",
    "url": "http://www.halleyweb.com/c066056/mc/mc_gridev_messi_datigrid.php?x=&tmphdata=1472542870851&combo1=9999",
    "feed": "http://feeds.ricostruzionetrasparente.it/albi_pretori/Montereale_feed.xml",
    "scraper": "https://github.com/ebergam/halley2RSS",
    "maintainer": "Enrico Bergamini <enrico.bergamini@ondata.it> (http://www.enricobergamini.it/)"
  },
  {
    "id": "c_l597_a",
    "title": "Albo Pretorio del Comune di Valle Castellana",
    "description": "*non ufficiale* RSS feed dell'Albo Pretorio di Valle Castellana",
    "administration": "Comune di Valle Castellana",
    "ipa_code": "c_l597",
    "istat_code": "67046",
    "url": "http://www.halleyweb.com/c067046/mc/mc_gridev_messi_datigrid.php?x=&tmphdata=1472496974183&combo1=9999",
    "feed": "http://feeds.ricostruzionetrasparente.it/albi_pretori/Valle Castellana_feed.xml",
    "scraper": "https://github.com/ebergam/halley2RSS",
    "maintainer": "Enrico Bergamini <enrico.bergamini@ondata.it> (http://www.enricobergamini.it/)"
  },
  {
    "id": "c_a019_a",
    "title": "Albo Pretorio del Comune di Accumoli",
    "description": "*non ufficiale* RSS feed dell'Albo Pretorio di Accumoli",
    "administration": "Comune di Accumoli",
    "ipa_code": "c_a019",
    "istat_code": "57001",
    "url": "http://www.halleyweb.com/c057001/mc/mc_gridev_messi_datigrid.php?x=&tmphdata=1472496974183&combo1=9999",
    "feed": "http://feeds.ricostruzionetrasparente.it/albi_pretori/Accumoli_feed.xml",
    "scraper": "https://github.com/ebergam/halley2RSS",
    "maintainer": "Enrico Bergamini <enrico.bergamini@ondata.it> (http://www.enricobergamini.it/)"
  },
  {
    "id": "c_a044_a",
    "title": "Albo Pretorio del Comune di Acquasanta Terme",
    "description": "*non ufficiale* RSS feed dell'Albo Pretorio di Acquasanta Terme",
    "administration": "Comune di Acquasanta Terme",
    "ipa_code": "c_a044",
    "istat_code": "44001",
    "url": "http://www.halleyweb.com/c044001/mc/mc_gridev_messi_datigrid.php?x=",
    "feed": "http://feeds.ricostruzionetrasparente.it/albi_pretori/Acquasanta Terme_feed.xml",
    "scraper": "https://github.com/ebergam/halley2RSS",
    "maintainer": "Enrico Bergamini <enrico.bergamini@ondata.it> (http://www.enricobergamini.it/)"
  },
  {
    "id": "c_a258_a",
    "title": "Albo Pretorio del Comune di Amatrice",
    "description": "*non ufficiale* RSS feed dell'Albo Pretorio di Amatrice",
    "administration": "Comune di Amatrice",
    "ipa_code": "c_a258",
    "istat_code": "57002",
    "url": "http://halleyweb.com/c057002/mc/mc_gridev_messi_datigrid.php?x=",
    "feed": "http://feeds.ricostruzionetrasparente.it/albi_pretori/Amatrice_feed.xml",
    "scraper": "https://github.com/ebergam/halley2RSS",
    "maintainer": "Enrico Bergamini <enrico.bergamini@ondata.it> (http://www.enricobergamini.it/)"
  },
  {
    "id": "c_a437_a",
    "title": "Albo Pretorio del Comune di Arquata del Tronto",
    "description": "*non ufficiale* RSS feed dell'Albo Pretorio di Arquata del Tronto",
    "administration": "Comune di Arquata del Tronto",
    "ipa_code": "c_a437",
    "istat_code": "44006",
    "url": "http://www.halleyweb.com/c044006/mc/mc_gridev_messi_datigrid.php?x=&tmphdata=1472496974183&combo1=9999",
    "feed": "http://feeds.ricostruzionetrasparente.it/albi_pretori/Arquata del Tronto_feed.xml",
    "scraper": "https://github.com/ebergam/halley2RSS",
    "maintainer": "Enrico Bergamini <enrico.bergamini@ondata.it> (http://www.enricobergamini.it/)"
  },
  {
    "id": "c_b658_a",
    "title": "Albo Pretorio del Comune di Capitignano",
    "description": "*non ufficiale* RSS feed dell'Albo Pretorio di Capitignano",
    "administration": "Comune di Capitignano",
    "ipa_code": "c_b658",
    "istat_code": "66021",
    "url": "http://www.halleyweb.com/c066021/mc/mc_gridev_messi_datigrid.php?x=&tmphdata=1472496974183&combo1=9999",
    "feed": "http://feeds.ricostruzionetrasparente.it/albi_pretori/Capitignano_feed.xml",
    "scraper": "https://github.com/ebergam/halley2RSS",
    "maintainer": "Enrico Bergamini <enrico.bergamini@ondata.it> (http://www.enricobergamini.it/)"
  },
  {
    "id": "c_b948_a",
    "title": "Albo Pretorio del Comune di Cascia",
    "description": "*non ufficiale* RSS feed dell'Albo Pretorio di Cascia",
    "administration": "Comune di Cascia",
    "ipa_code": "c_b948",
    "istat_code": "54007",
    "url": "http://www.halleyweb.com/c054007/mc/mc_gridev_messi_datigrid.php?x=",
    "feed": "http://feeds.ricostruzionetrasparente.it/albi_pretori/Cascia_feed.xml",
    "scraper": "https://github.com/ebergam/halley2RSS",
    "maintainer": "Enrico Bergamini <enrico.bergamini@ondata.it> (http://www.enricobergamini.it/)"
  },
  {
    "id": "c_c749_a",
    "title": "Albo Pretorio del Comune di Cittareale",
    "description": "*non ufficiale* RSS feed dell'Albo Pretorio di Cittareale",
    "administration": "Comune di Cittareale",
    "ipa_code": "c_c749",
    "istat_code": "57017",
    "url": "http://www.halleyweb.com/c057017/mc/mc_gridev_messi_datigrid.php?x=&tmphdata=1472496974183&combo1=9999",
    "feed": "http://feeds.ricostruzionetrasparente.it/albi_pretori/Cittareale_feed.xml",
    "scraper": "https://github.com/ebergam/halley2RSS",
    "maintainer": "Enrico Bergamini <enrico.bergamini@ondata.it> (http://www.enricobergamini.it/)"
  },
  {
    "id": "c_f509_a",
    "title": "Albo Pretorio del Comune di Montefortino",
    "description": "*non ufficiale* RSS feed dell'Albo Pretorio di Montefortino",
    "administration": "Comune di Montefortino",
    "ipa_code": "c_f509",
    "istat_code": "109015",
    "url": "http://www.halleyweb.com/c044037/mc/mc_gridev_messi_datigrid.php?x=&tmphdata=1472496974183&combo1=9999",
    "feed": "http://feeds.ricostruzionetrasparente.it/albi_pretori/Montefortino_feed.xml",
    "scraper": "https://github.com/ebergam/halley2RSS",
    "maintainer": "Enrico Bergamini <enrico.bergamini@ondata.it> (http://www.enricobergamini.it/)"
  },
  {
    "id": "c_f516_a",
    "title": "Albo Pretorio del Comune di Montegallo",
    "description": "*non ufficiale* RSS feed dell'Albo Pretorio di Montegallo",
    "administration": "Comune di Montegallo",
    "ipa_code": "c_f516",
    "istat_code": "44038",
    "url": "http://www.halleyweb.com/c044038/mc/mc_gridev_messi_datigrid.php?x=&tmphdata=1472496974183&combo1=9999",
    "feed": "http://feeds.ricostruzionetrasparente.it/albi_pretori/Montegallo_feed.xml",
    "scraper": "https://github.com/ebergam/halley2RSS",
    "maintainer": "Enrico Bergamini <enrico.bergamini@ondata.it> (http://www.enricobergamini.it/)"
  },
  {
    "id": "c_f540_a",
    "title": "Albo Pretorio del Comune di Monteleone di Spoleto",
    "description": "*non ufficiale* RSS feed dell'Albo Pretorio di Monteleone di Spoleto",
    "administration": "Comune di Monteleone di Spoleto",
    "ipa_code": "c_f540",
    "istat_code": "54031",
    "url": "http://www.halleyweb.com/c054031/mc/mc_gridev_messi_datigrid.php?x=&tmphdata=1472496974183&combo1=9999",
    "feed": "http://feeds.ricostruzionetrasparente.it/albi_pretori/Monteleone di Spoleto_feed.xml",
    "scraper": "https://github.com/ebergam/halley2RSS",
    "maintainer": "Enrico Bergamini <enrico.bergamini@ondata.it> (http://www.enricobergamini.it/)"
  },
  {
    "id": "c_f570_a",
    "title": "Albo Pretorio del Comune di Montemonaco",
    "description": "*non ufficiale* RSS feed dell'Albo Pretorio di Montemonaco",
    "administration": "Comune di Montemonaco",
    "ipa_code": "c_f570",
    "istat_code": "44044",
    "url": "http://www.tecuting.it/c044044/mc/mc_gridev_messi_datigrid.php?x=",
    "feed": "http://feeds.ricostruzionetrasparente.it/albi_pretori/Montemonaco_feed.xml",
    "scraper": "https://github.com/ebergam/halley2RSS",
    "maintainer": "Enrico Bergamini <enrico.bergamini@ondata.it> (http://www.enricobergamini.it/)"
  },
  {
    "id": "c_f935_a",
    "title": "Albo Pretorio del Comune di Norcia",
    "description": "*non ufficiale* RSS feed dell'Albo Pretorio di Norcia",
    "administration": "Comune di Norcia",
    "ipa_code": "c_f935",
    "istat_code": "54035",
    "url": "http://www.halleyweb.com/c054035/mc/mc_gridev_messi_datigrid.php?x=",
    "feed": "http://feeds.ricostruzionetrasparente.it/albi_pretori/Norcia_feed.xml",
    "scraper": "https://github.com/ebergam/halley2RSS",
    "maintainer": "Enrico Bergamini <enrico.bergamini@ondata.it> (http://www.enricobergamini.it/)"
  },
  {
    "id": "c_h440_a",
    "title": "Albo Pretorio del Comune di Rocca Santa Maria",
    "description": "*non ufficiale* RSS feed dell'Albo Pretorio di Rocca Santa Maria",
    "administration": "Comune di Rocca Santa Maria",
    "ipa_code": "c_h440",
    "istat_code": "67036",
    "url": "http://www.halleyweb.com/c067036/mc/mc_gridev_messi_datigrid.php?x=&tmphdata=1472496974183&combo1=9999",
    "feed": "http://feeds.ricostruzionetrasparente.it/albi_pretori/Rocca Santa Maria_feed.xml",
    "scraper": "https://github.com/ebergam/halley2RSS",
    "maintainer": "Enrico Bergamini <enrico.bergamini@ondata.it> (http://www.enricobergamini.it/)"
  },
  {
    "id": "c_a252_a",
    "title": "Albo Pretorio del Comune di Amandola",
    "description": "*non ufficiale* RSS feed dell'Albo Pretorio di Amandola",
    "administration": "Comune di Amandola",
    "ipa_code": "c_a252",
    "istat_code": "44004",
    "url": "http://www.halleyweb.com/c044004/mc/mc_gridev_messi_datigrid.php?x=&tmphdata=1472496974183&combo1=9999",
    "feed": "http://feeds.ricostruzionetrasparente.it/albi_pretori/Amandola_feed.xml",
    "scraper": "https://github.com/ebergam/halley2RSS",
    "maintainer": "Enrico Bergamini <enrico.bergamini@ondata.it> (http://www.enricobergamini.it/)"
  },
  {
    "id": "c_a315_a",
    "title": "Albo Pretorio del Comune di Antrodoco",
    "description": "*non ufficiale* RSS feed dell'Albo Pretorio di Antrodoco",
    "administration": "Comune di Antrodoco",
    "ipa_code": "c_a315",
    "istat_code": "57003",
    "url": "http://www.halleyweb.com/c057003/mc/mc_gridev_messi_datigrid.php?x=&tmphdata=1472496974183&combo1=9999",
    "feed": "http://feeds.ricostruzionetrasparente.it/albi_pretori/Antrodoco_feed.xml",
    "scraper": "https://github.com/ebergam/halley2RSS",
    "maintainer": "Enrico Bergamini <enrico.bergamini@ondata.it> (http://www.enricobergamini.it/)"
  },
  {
    "id": "c_a335_a",
    "title": "Albo Pretorio del Comune di Appignano del Tronto",
    "description": "*non ufficiale* RSS feed dell'Albo Pretorio di Appignano del Tronto",
    "administration": "Comune di Appignano del Tronto",
    "ipa_code": "c_a335",
    "istat_code": "44005",
    "url": "http://www.halleyweb.com/c044005/mc/mc_gridev_messi_datigrid.php?x=&tmphdata=1472496974183&combo1=9999",
    "feed": "http://feeds.ricostruzionetrasparente.it/albi_pretori/Appignano del Tronto_feed.xml",
    "scraper": "https://github.com/ebergam/halley2RSS",
    "maintainer": "Enrico Bergamini <enrico.bergamini@ondata.it> (http://www.enricobergamini.it/)"
  },
  {
    "id": "c_a760_a",
    "title": "Albo Pretorio del Comune di Belmonte Piceno",
    "description": "*non ufficiale* RSS feed dell'Albo Pretorio di Belmonte Piceno",
    "administration": "Comune di Belmonte Piceno",
    "ipa_code": "c_a760",
    "istat_code": "44008",
    "url": "http://www.halleyweb.com/c044008/mc/mc_gridev_messi_datigrid.php?x=&tmphdata=1472496974183&combo1=9999",
    "feed": "http://feeds.ricostruzionetrasparente.it/albi_pretori/Belmonte Piceno_feed.xml",
    "scraper": "https://github.com/ebergam/halley2RSS",
    "maintainer": "Enrico Bergamini <enrico.bergamini@ondata.it> (http://www.enricobergamini.it/)"
  },
  {
    "id": "c_a947_a",
    "title": "Albo Pretorio del Comune di Bolognola",
    "description": "*non ufficiale* RSS feed dell'Albo Pretorio di Bolognola",
    "administration": "Comune di Bolognola",
    "ipa_code": "c_a947",
    "istat_code": "43005",
    "url": "http://www.halleyweb.com/c043005/mc/mc_gridev_messi_datigrid.php?x=&tmphdata=1472496974183&combo1=9999",
    "feed": "http://feeds.ricostruzionetrasparente.it/albi_pretori/Bolognola_feed.xml",
    "scraper": "https://github.com/ebergam/halley2RSS",
    "maintainer": "Enrico Bergamini <enrico.bergamini@ondata.it> (http://www.enricobergamini.it/)"
  },
  {
    "id": "c_a981_a",
    "title": "Albo Pretorio del Comune di Borbona",
    "description": "*non ufficiale* RSS feed dell'Albo Pretorio di Borbona",
    "administration": "Comune di Borbona",
    "ipa_code": "c_a981",
    "istat_code": "57006",
    "url": "http://www.halleyweb.com/c057006/mc/mc_gridev_messi_datigrid.php?x=&tmphdata=1472496974183&combo1=9999",
    "feed": "http://feeds.ricostruzionetrasparente.it/albi_pretori/Borbona_feed.xml",
    "scraper": "https://github.com/ebergam/halley2RSS",
    "maintainer": "Enrico Bergamini <enrico.bergamini@ondata.it> (http://www.enricobergamini.it/)"
  },
  {
    "id": "c_a996_a",
    "title": "Albo Pretorio del Comune di Borgo Velino",
    "description": "*non ufficiale* RSS feed dell'Albo Pretorio di Borgo Velino",
    "administration": "Comune di Borgo Velino",
    "ipa_code": "c_a996",
    "istat_code": "57008",
    "url": "http://www.halleyweb.com/c057008/mc/mc_gridev_messi_datigrid.php?x=&tmphdata=1472496974183&combo1=9999",
    "feed": "http://feeds.ricostruzionetrasparente.it/albi_pretori/Borgo Velino_feed.xml",
    "scraper": "https://github.com/ebergam/halley2RSS",
    "maintainer": "Enrico Bergamini <enrico.bergamini@ondata.it> (http://www.enricobergamini.it/)"
  },
  {
    "id": "c_b398_a",
    "title": "Albo Pretorio del Comune di Caldarola",
    "description": "*non ufficiale* RSS feed dell'Albo Pretorio di Caldarola",
    "administration": "Comune di Caldarola",
    "ipa_code": "c_b398",
    "istat_code": "43006",
    "url": "http://www.halleyweb.com/c043006/mc/mc_gridev_messi_datigrid.php?x=&tmphdata=1472496974183&combo1=9999",
    "feed": "http://feeds.ricostruzionetrasparente.it/albi_pretori/Caldarola_feed.xml",
    "scraper": "https://github.com/ebergam/halley2RSS",
    "maintainer": "Enrico Bergamini <enrico.bergamini@ondata.it> (http://www.enricobergamini.it/)"
  },
  {
    "id": "c_b474_a",
    "title": "Albo Pretorio del Comune di Camerino",
    "description": "*non ufficiale* RSS feed dell'Albo Pretorio di Camerino",
    "administration": "Comune di Camerino",
    "ipa_code": "c_b474",
    "istat_code": "43007",
    "url": "http://www.halleyweb.com/c043007/mc/mc_gridev_messi_datigrid.php?x=&tmphdata=1472496974183&combo1=9999",
    "feed": "http://feeds.ricostruzionetrasparente.it/albi_pretori/Camerino_feed.xml",
    "scraper": "https://github.com/ebergam/halley2RSS",
    "maintainer": "Enrico Bergamini <enrico.bergamini@ondata.it> (http://www.enricobergamini.it/)"
  },
  {
    "id": "c_c070_a",
    "title": "Albo Pretorio del Comune di Servigliano",
    "description": "*non ufficiale* RSS feed dell'Albo Pretorio di Servigliano",
    "administration": "Comune di Servigliano",
    "ipa_code": "c_c070",
    "istat_code": "44069",
    "url": "http://www.halleyweb.com/c044069/mc/mc_gridev_messi_datigrid.php?x=&tmphdata=1472496974183&combo1=9999",
    "feed": "http://feeds.ricostruzionetrasparente.it/albi_pretori/Servigliano_feed.xml",
    "scraper": "https://github.com/ebergam/halley2RSS",
    "maintainer": "Enrico Bergamini <enrico.bergamini@ondata.it> (http://www.enricobergamini.it/)"
  },
  {
    "id": "c_c093_a",
    "title": "Albo Pretorio del Comune di Castel di Lama",
    "description": "*non ufficiale* RSS feed dell'Albo Pretorio di Castel di Lama",
    "administration": "Comune di Castel di Lama",
    "ipa_code": "c_c093",
    "istat_code": "44011",
    "url": "http://www.halleyweb.com/c044011/mc/mc_gridev_messi_datigrid.php?x=&tmphdata=1472496974183&combo1=9999",
    "feed": "http://feeds.ricostruzionetrasparente.it/albi_pretori/Castel di Lama_feed.xml",
    "scraper": "https://github.com/ebergam/halley2RSS",
    "maintainer": "Enrico Bergamini <enrico.bergamini@ondata.it> (http://www.enricobergamini.it/)"
  },
  {
    "id": "c_c169_a",
    "title": "Albo Pretorio del Comune di Castelli",
    "description": "*non ufficiale* RSS feed dell'Albo Pretorio di Castelli",
    "administration": "Comune di Castelli",
    "ipa_code": "c_c169",
    "istat_code": "67012",
    "url": "http://www.halleyweb.com/c067012/mc/mc_gridev_messi_datigrid.php?x=&tmphdata=1472496974183&combo1=9999",
    "feed": "http://feeds.ricostruzionetrasparente.it/albi_pretori/Castelli_feed.xml",
    "scraper": "https://github.com/ebergam/halley2RSS",
    "maintainer": "Enrico Bergamini <enrico.bergamini@ondata.it> (http://www.enricobergamini.it/)"
  },
  {
    "id": "c_c251_a",
    "title": "Albo Pretorio del Comune di Castelraimondo",
    "description": "*non ufficiale* RSS feed dell'Albo Pretorio di Castelraimondo",
    "administration": "Comune di Castelraimondo",
    "ipa_code": "c_c251",
    "istat_code": "43009",
    "url": "http://www.halleyweb.com/c043009/mc/mc_gridev_messi_datigrid.php?x=&tmphdata=1472496974183&combo1=9999",
    "feed": "http://feeds.ricostruzionetrasparente.it/albi_pretori/Castelraimondo_feed.xml",
    "scraper": "https://github.com/ebergam/halley2RSS",
    "maintainer": "Enrico Bergamini <enrico.bergamini@ondata.it> (http://www.enricobergamini.it/)"
  },
  {
    "id": "c_c267_a",
    "title": "Albo Pretorio del Comune di Castelsantangelo sul Nera",
    "description": "*non ufficiale* RSS feed dell'Albo Pretorio di Castelsantangelo sul Nera",
    "administration": "Comune di Castelsantangelo sul Nera",
    "ipa_code": "c_c267",
    "istat_code": "43010",
    "url": "http://www.halleyweb.com/c043010/mc/mc_gridev_messi_datigrid.php?x=&tmphdata=1472496974183&combo1=9999",
    "feed": "http://feeds.ricostruzionetrasparente.it/albi_pretori/Castelsantangelo sul Nera_feed.xml",
    "scraper": "https://github.com/ebergam/halley2RSS",
    "maintainer": "Enrico Bergamini <enrico.bergamini@ondata.it> (http://www.enricobergamini.it/)"
  },
  {
    "id": "c_c268_a",
    "title": "Albo Pretorio del Comune di Castel Sant'Angelo",
    "description": "*non ufficiale* RSS feed dell'Albo Pretorio di Castel Sant'Angelo",
    "administration": "Comune di Castel Sant'Angelo",
    "ipa_code": "c_c268",
    "istat_code": "57015",
    "url": "http://www.halleyweb.com/c057015/mc/mc_gridev_messi_datigrid.php?x=&tmphdata=1472496974183&combo1=9999",
    "feed": "http://feeds.ricostruzionetrasparente.it/albi_pretori/Castel Sant'Angelo_feed.xml",
    "scraper": "https://github.com/ebergam/halley2RSS",
    "maintainer": "Enrico Bergamini <enrico.bergamini@ondata.it> (http://www.enricobergamini.it/)"
  },
  {
    "id": "c_c321_a",
    "title": "Albo Pretorio del Comune di Castignano",
    "description": "*non ufficiale* RSS feed dell'Albo Pretorio di Castignano",
    "administration": "Comune di Castignano",
    "ipa_code": "c_c321",
    "istat_code": "44012",
    "url": "http://www.halleyweb.com/c044012/mc/mc_gridev_messi_datigrid.php?x=&tmphdata=1472496974183&combo1=9999",
    "feed": "http://feeds.ricostruzionetrasparente.it/albi_pretori/Castignano_feed.xml",
    "scraper": "https://github.com/ebergam/halley2RSS",
    "maintainer": "Enrico Bergamini <enrico.bergamini@ondata.it> (http://www.enricobergamini.it/)"
  },
  {
    "id": "c_c331_a",
    "title": "Albo Pretorio del Comune di Castorano",
    "description": "*non ufficiale* RSS feed dell'Albo Pretorio di Castorano",
    "administration": "Comune di Castorano",
    "ipa_code": "c_c331",
    "istat_code": "44013",
    "url": "http://www.halleyweb.com/c044013/mc/mc_gridev_messi_datigrid.php?x=&tmphdata=1472496974183&combo1=9999",
    "feed": "http://feeds.ricostruzionetrasparente.it/albi_pretori/Castorano_feed.xml",
    "scraper": "https://github.com/ebergam/halley2RSS",
    "maintainer": "Enrico Bergamini <enrico.bergamini@ondata.it> (http://www.enricobergamini.it/)"
  },
  {
    "id": "c_c527_a",
    "title": "Albo Pretorio del Comune di Cerreto di Spoleto",
    "description": "*non ufficiale* RSS feed dell'Albo Pretorio di Cerreto di Spoleto",
    "administration": "Comune di Cerreto di Spoleto",
    "ipa_code": "c_c527",
    "istat_code": "54010",
    "url": "http://www.halleyweb.com/c054010/mc/mc_gridev_messi_datigrid.php?x=&tmphdata=1472496974183&combo1=9999",
    "feed": "http://feeds.ricostruzionetrasparente.it/albi_pretori/Cerreto di Spoleto_feed.xml",
    "scraper": "https://github.com/ebergam/halley2RSS",
    "maintainer": "Enrico Bergamini <enrico.bergamini@ondata.it> (http://www.enricobergamini.it/)"
  },
  {
    "id": "c_c704_a",
    "title": "Albo Pretorio del Comune di Cingoli",
    "description": "*non ufficiale* RSS feed dell'Albo Pretorio di Cingoli",
    "administration": "Comune di Cingoli",
    "ipa_code": "c_c704",
    "istat_code": "43012",
    "url": "http://www.halleyweb.com/c043012/mc/mc_gridev_messi_datigrid.php?x=&tmphdata=1472496974183&combo1=9999",
    "feed": "http://feeds.ricostruzionetrasparente.it/albi_pretori/Cingoli_feed.xml",
    "scraper": "https://github.com/ebergam/halley2RSS",
    "maintainer": "Enrico Bergamini <enrico.bergamini@ondata.it> (http://www.enricobergamini.it/)"
  },
  {
    "id": "c_c781_a",
    "title": "Albo Pretorio del Comune di Civitella del Tronto",
    "description": "*non ufficiale* RSS feed dell'Albo Pretorio di Civitella del Tronto",
    "administration": "Comune di Civitella del Tronto",
    "ipa_code": "c_c781",
    "istat_code": "67017",
    "url": "http://www.halleyweb.com/c067017/mc/mc_gridev_messi_datigrid.php?x=&tmphdata=1472496974183&combo1=9999",
    "feed": "http://feeds.ricostruzionetrasparente.it/albi_pretori/Civitella del Tronto_feed.xml",
    "scraper": "https://github.com/ebergam/halley2RSS",
    "maintainer": "Enrico Bergamini <enrico.bergamini@ondata.it> (http://www.enricobergamini.it/)"
  },
  {
    "id": "c_c877_a",
    "title": "Albo Pretorio del Comune di Colli del Tronto",
    "description": "*non ufficiale* RSS feed dell'Albo Pretorio di Colli del Tronto",
    "administration": "Comune di Colli del Tronto",
    "ipa_code": "c_c877",
    "istat_code": "44014",
    "url": "http://www.halleyweb.com/c044014/mc/mc_gridev_messi_datigrid.php?x=&tmphdata=1472496974183&combo1=9999",
    "feed": "http://feeds.ricostruzionetrasparente.it/albi_pretori/Colli del Tronto_feed.xml",
    "scraper": "https://github.com/ebergam/halley2RSS",
    "maintainer": "Enrico Bergamini <enrico.bergamini@ondata.it> (http://www.enricobergamini.it/)"
  },
  {
    "id": "c_c886_a",
    "title": "Albo Pretorio del Comune di Colmurano",
    "description": "*non ufficiale* RSS feed dell'Albo Pretorio di Colmurano",
    "administration": "Comune di Colmurano",
    "ipa_code": "c_c886",
    "istat_code": "43014",
    "url": "http://www.halleyweb.com/c043014/mc/mc_gridev_messi_datigrid.php?x=&tmphdata=1472496974183&combo1=9999",
    "feed": "http://feeds.ricostruzionetrasparente.it/albi_pretori/Colmurano_feed.xml",
    "scraper": "https://github.com/ebergam/halley2RSS",
    "maintainer": "Enrico Bergamini <enrico.bergamini@ondata.it> (http://www.enricobergamini.it/)"
  },
  {
    "id": "c_c935_a",
    "title": "Albo Pretorio del Comune di Comunanza",
    "description": "*non ufficiale* RSS feed dell'Albo Pretorio di Comunanza",
    "administration": "Comune di Comunanza",
    "ipa_code": "c_c935",
    "istat_code": "44015",
    "url": "http://www.halleyweb.com/c044015/mc/mc_gridev_messi_datigrid.php?x=&tmphdata=1472496974183&combo1=9999",
    "feed": "http://feeds.ricostruzionetrasparente.it/albi_pretori/Comunanza_feed.xml",
    "scraper": "https://github.com/ebergam/halley2RSS",
    "maintainer": "Enrico Bergamini <enrico.bergamini@ondata.it> (http://www.enricobergamini.it/)"
  },
  {
    "id": "c_d042_a",
    "title": "Albo Pretorio del Comune di Corridonia",
    "description": "*non ufficiale* RSS feed dell'Albo Pretorio di Corridonia",
    "administration": "Comune di Corridonia",
    "ipa_code": "c_d042",
    "istat_code": "43015",
    "url": "http://www.halleyweb.com/c043015/mc/mc_gridev_messi_datigrid.php?x=&tmphdata=1472496974183&combo1=9999",
    "feed": "http://feeds.ricostruzionetrasparente.it/albi_pretori/Corridonia_feed.xml",
    "scraper": "https://github.com/ebergam/halley2RSS",
    "maintainer": "Enrico Bergamini <enrico.bergamini@ondata.it> (http://www.enricobergamini.it/)"
  },
  {
    "id": "c_d076_a",
    "title": "Albo Pretorio del Comune di Cortino",
    "description": "*non ufficiale* RSS feed dell'Albo Pretorio di Cortino",
    "administration": "Comune di Cortino",
    "ipa_code": "c_d076",
    "istat_code": "67022",
    "url": "http://www.halleyweb.com/c067022/mc/mc_gridev_messi_datigrid.php?x=&tmphdata=1472496974183&combo1=9999",
    "feed": "http://feeds.ricostruzionetrasparente.it/albi_pretori/Cortino_feed.xml",
    "scraper": "https://github.com/ebergam/halley2RSS",
    "maintainer": "Enrico Bergamini <enrico.bergamini@ondata.it> (http://www.enricobergamini.it/)"
  },
  {
    "id": "c_d096_a",
    "title": "Albo Pretorio del Comune di Cossignano",
    "description": "*non ufficiale* RSS feed dell'Albo Pretorio di Cossignano",
    "administration": "Comune di Cossignano",
    "ipa_code": "c_d096",
    "istat_code": "44016",
    "url": "http://www.halleyweb.com/c044016/mc/mc_gridev_messi_datigrid.php?x=&tmphdata=1472496974183&combo1=9999",
    "feed": "http://feeds.ricostruzionetrasparente.it/albi_pretori/Cossignano_feed.xml",
    "scraper": "https://github.com/ebergam/halley2RSS",
    "maintainer": "Enrico Bergamini <enrico.bergamini@ondata.it> (http://www.enricobergamini.it/)"
  },
  {
    "id": "c_d179_a",
    "title": "Albo Pretorio del Comune di Crognaleto",
    "description": "*non ufficiale* RSS feed dell'Albo Pretorio di Crognaleto",
    "administration": "Comune di Crognaleto",
    "ipa_code": "c_d179",
    "istat_code": "67023",
    "url": "http://www.halleyweb.com/c067023/mc/mc_gridev_messi_datigrid.php?x=&tmphdata=1472496974183&combo1=9999",
    "feed": "http://feeds.ricostruzionetrasparente.it/albi_pretori/Crognaleto_feed.xml",
    "scraper": "https://github.com/ebergam/halley2RSS",
    "maintainer": "Enrico Bergamini <enrico.bergamini@ondata.it> (http://www.enricobergamini.it/)"
  },
  {
    "id": "c_d477_a",
    "title": "Albo Pretorio del Comune di Falerone",
    "description": "*non ufficiale* RSS feed dell'Albo Pretorio di Falerone",
    "administration": "Comune di Falerone",
    "ipa_code": "c_d477",
    "istat_code": "44018",
    "url": "http://www.halleyweb.com/c044018/mc/mc_gridev_messi_datigrid.php?x=&tmphdata=1472496974183&combo1=9999",
    "feed": "http://feeds.ricostruzionetrasparente.it/albi_pretori/Falerone_feed.xml",
    "scraper": "https://github.com/ebergam/halley2RSS",
    "maintainer": "Enrico Bergamini <enrico.bergamini@ondata.it> (http://www.enricobergamini.it/)"
  },
  {
    "id": "c_d564_a",
    "title": "Albo Pretorio del Comune di Fiastra",
    "description": "*non ufficiale* RSS feed dell'Albo Pretorio di Fiastra",
    "administration": "Comune di Fiastra",
    "ipa_code": "c_d564",
    "istat_code": "44017",
    "url": "http://www.halleyweb.com/c044017/mc/mc_gridev_messi_datigrid.php?x=&tmphdata=1472496974183&combo1=9999",
    "feed": "http://feeds.ricostruzionetrasparente.it/albi_pretori/Fiastra_feed.xml",
    "scraper": "https://github.com/ebergam/halley2RSS",
    "maintainer": "Enrico Bergamini <enrico.bergamini@ondata.it> (http://www.enricobergamini.it/)"
  },
  {
    "id": "c_d566_a",
    "title": "Albo Pretorio del Comune di Poggio San Vicino",
    "description": "*non ufficiale* RSS feed dell'Albo Pretorio di Poggio San Vicino",
    "administration": "Comune di Poggio San Vicino",
    "ipa_code": "c_d566",
    "istat_code": "43040",
    "url": "http://www.halleyweb.com/c043040/mc/mc_gridev_messi_datigrid.php?x=&tmphdata=1472496974183&combo1=9999",
    "feed": "http://feeds.ricostruzionetrasparente.it/albi_pretori/Poggio San Vicino_feed.xml",
    "scraper": "https://github.com/ebergam/halley2RSS",
    "maintainer": "Enrico Bergamini <enrico.bergamini@ondata.it> (http://www.enricobergamini.it/)"
  },
  {
    "id": "c_d609_a",
    "title": "Albo Pretorio del Comune di Fiordimonte",
    "description": "*non ufficiale* RSS feed dell'Albo Pretorio di Fiordimonte",
    "administration": "Comune di Fiordimonte",
    "ipa_code": "c_d609",
    "istat_code": "43018",
    "url": "http://www.halleyweb.com/c043018/mc/mc_gridev_messi_datigrid.php?x=&tmphdata=1472496974183&combo1=9999",
    "feed": "http://feeds.ricostruzionetrasparente.it/albi_pretori/Fiordimonte_feed.xml",
    "scraper": "https://github.com/ebergam/halley2RSS",
    "maintainer": "Enrico Bergamini <enrico.bergamini@ondata.it> (http://www.enricobergamini.it/)"
  },
  {
    "id": "c_d628_a",
    "title": "Albo Pretorio del Comune di Fiuminata",
    "description": "*non ufficiale* RSS feed dell'Albo Pretorio di Fiuminata",
    "administration": "Comune di Fiuminata",
    "ipa_code": "c_d628",
    "istat_code": "43019",
    "url": "http://www.halleyweb.com/c043019/mc/mc_gridev_messi_datigrid.php?x=&tmphdata=1472496974183&combo1=9999",
    "feed": "http://feeds.ricostruzionetrasparente.it/albi_pretori/Fiuminata_feed.xml",
    "scraper": "https://github.com/ebergam/halley2RSS",
    "maintainer": "Enrico Bergamini <enrico.bergamini@ondata.it> (http://www.enricobergamini.it/)"
  },
  {
    "id": "c_d652_a",
    "title": "Albo Pretorio del Comune di Folignano",
    "description": "*non ufficiale* RSS feed dell'Albo Pretorio di Folignano",
    "administration": "Comune di Folignano",
    "ipa_code": "c_d652",
    "istat_code": "44020",
    "url": "http://www.halleyweb.com/c044020/mc/mc_gridev_messi_datigrid.php?x=&tmphdata=1472496974183&combo1=9999",
    "feed": "http://feeds.ricostruzionetrasparente.it/albi_pretori/Folignano_feed.xml",
    "scraper": "https://github.com/ebergam/halley2RSS",
    "maintainer": "Enrico Bergamini <enrico.bergamini@ondata.it> (http://www.enricobergamini.it/)"
  },
  {
    "id": "c_d691_a",
    "title": "Albo Pretorio del Comune di Force",
    "description": "*non ufficiale* RSS feed dell'Albo Pretorio di Force",
    "administration": "Comune di Force",
    "ipa_code": "c_d691",
    "istat_code": "44021",
    "url": "http://www.halleyweb.com/c044021/mc/mc_gridev_messi_datigrid.php?x=&tmphdata=1472496974183&combo1=9999",
    "feed": "http://feeds.ricostruzionetrasparente.it/albi_pretori/Force_feed.xml",
    "scraper": "https://github.com/ebergam/halley2RSS",
    "maintainer": "Enrico Bergamini <enrico.bergamini@ondata.it> (http://www.enricobergamini.it/)"
  },
  {
    "id": "c_d853_a",
    "title": "Albo Pretorio del Comune di Gagliole",
    "description": "*non ufficiale* RSS feed dell'Albo Pretorio di Gagliole",
    "administration": "Comune di Gagliole",
    "ipa_code": "c_d853",
    "istat_code": "43020",
    "url": "http://www.halleyweb.com/c043020/mc/mc_gridev_messi_datigrid.php?x=&tmphdata=1472496974183&combo1=9999",
    "feed": "http://feeds.ricostruzionetrasparente.it/albi_pretori/Gagliole_feed.xml",
    "scraper": "https://github.com/ebergam/halley2RSS",
    "maintainer": "Enrico Bergamini <enrico.bergamini@ondata.it> (http://www.enricobergamini.it/)"
  },
  {
    "id": "c_e228_a",
    "title": "Albo Pretorio del Comune di Gualdo",
    "description": "*non ufficiale* RSS feed dell'Albo Pretorio di Gualdo",
    "administration": "Comune di Gualdo",
    "ipa_code": "c_e228",
    "istat_code": "43021",
    "url": "http://www.halleyweb.com/c043021/mc/mc_gridev_messi_datigrid.php?x=&tmphdata=1472496974183&combo1=9999",
    "feed": "http://feeds.ricostruzionetrasparente.it/albi_pretori/Gualdo_feed.xml",
    "scraper": "https://github.com/ebergam/halley2RSS",
    "maintainer": "Enrico Bergamini <enrico.bergamini@ondata.it> (http://www.enricobergamini.it/)"
  },
  {
    "id": "c_e694_a",
    "title": "Albo Pretorio del Comune di Loro Piceno",
    "description": "*non ufficiale* RSS feed dell'Albo Pretorio di Loro Piceno",
    "administration": "Comune di Loro Piceno",
    "ipa_code": "c_e694",
    "istat_code": "43022",
    "url": "http://www.halleyweb.com/c043022/mc/mc_gridev_messi_datigrid.php?x=&tmphdata=1472496974183&combo1=9999",
    "feed": "http://feeds.ricostruzionetrasparente.it/albi_pretori/Loro Piceno_feed.xml",
    "scraper": "https://github.com/ebergam/halley2RSS",
    "maintainer": "Enrico Bergamini <enrico.bergamini@ondata.it> (http://www.enricobergamini.it/)"
  },
  {
    "id": "c_f021_a",
    "title": "Albo Pretorio del Comune di Massa Fermana",
    "description": "*non ufficiale* RSS feed dell'Albo Pretorio di Massa Fermana",
    "administration": "Comune di Massa Fermana",
    "ipa_code": "c_f021",
    "istat_code": "109011",
    "url": "http://www.halleyweb.com/c109011/mc/mc_gridev_messi_datigrid.php?x=&tmphdata=1472496974183&combo1=9999",
    "feed": "http://feeds.ricostruzionetrasparente.it/albi_pretori/Massa Fermana_feed.xml",
    "scraper": "https://github.com/ebergam/halley2RSS",
    "maintainer": "Enrico Bergamini <enrico.bergamini@ondata.it> (http://www.enricobergamini.it/)"
  },
  {
    "id": "c_f051_a",
    "title": "Albo Pretorio del Comune di Matelica",
    "description": "*non ufficiale* RSS feed dell'Albo Pretorio di Matelica",
    "administration": "Comune di Matelica",
    "ipa_code": "c_f051",
    "istat_code": "43024",
    "url": "http://www.halleyweb.com/c043024/mc/mc_gridev_messi_datigrid.php?x=&tmphdata=1472496974183&combo1=9999",
    "feed": "http://feeds.ricostruzionetrasparente.it/albi_pretori/Matelica_feed.xml",
    "scraper": "https://github.com/ebergam/halley2RSS",
    "maintainer": "Enrico Bergamini <enrico.bergamini@ondata.it> (http://www.enricobergamini.it/)"
  },
  {
    "id": "c_f193_a",
    "title": "Albo Pretorio del Comune di Micigliano",
    "description": "*non ufficiale* RSS feed dell'Albo Pretorio di Micigliano",
    "administration": "Comune di Micigliano",
    "ipa_code": "c_f193",
    "istat_code": "57037",
    "url": "http://www.halleyweb.com/c057037/mc/mc_gridev_messi_datigrid.php?x=&tmphdata=1472496974183&combo1=9999",
    "feed": "http://feeds.ricostruzionetrasparente.it/albi_pretori/Micigliano_feed.xml",
    "scraper": "https://github.com/ebergam/halley2RSS",
    "maintainer": "Enrico Bergamini <enrico.bergamini@ondata.it> (http://www.enricobergamini.it/)"
  },
  {
    "id": "c_f268_a",
    "title": "Albo Pretorio del Comune di Mogliano",
    "description": "*non ufficiale* RSS feed dell'Albo Pretorio di Mogliano",
    "administration": "Comune di Mogliano",
    "ipa_code": "c_f268",
    "istat_code": "43025",
    "url": "http://www.halleyweb.com/c043025/mc/mc_gridev_messi_datigrid.php?x=&tmphdata=1472496974183&combo1=9999",
    "feed": "http://feeds.ricostruzionetrasparente.it/albi_pretori/Mogliano_feed.xml",
    "scraper": "https://github.com/ebergam/halley2RSS",
    "maintainer": "Enrico Bergamini <enrico.bergamini@ondata.it> (http://www.enricobergamini.it/)"
  },
  {
    "id": "c_f379_a",
    "title": "Albo Pretorio del Comune di Monsampietro Morico",
    "description": "*non ufficiale* RSS feed dell'Albo Pretorio di Monsampietro Morico",
    "administration": "Comune di Monsampietro Morico",
    "ipa_code": "c_f379",
    "istat_code": "44030",
    "url": "http://www.halleyweb.com/c044030/mc/mc_gridev_messi_datigrid.php?x=&tmphdata=1472496974183&combo1=9999",
    "feed": "http://feeds.ricostruzionetrasparente.it/albi_pretori/Monsampietro Morico_feed.xml",
    "scraper": "https://github.com/ebergam/halley2RSS",
    "maintainer": "Enrico Bergamini <enrico.bergamini@ondata.it> (http://www.enricobergamini.it/)"
  },
  {
    "id": "c_f415_a",
    "title": "Albo Pretorio del Comune di Montalto delle Marche",
    "description": "*non ufficiale* RSS feed dell'Albo Pretorio di Montalto delle Marche",
    "administration": "Comune di Montalto delle Marche",
    "ipa_code": "c_f415",
    "istat_code": "44032",
    "url": "http://www.halleyweb.com/c044032/mc/mc_gridev_messi_datigrid.php?x=&tmphdata=1472496974183&combo1=9999",
    "feed": "http://feeds.ricostruzionetrasparente.it/albi_pretori/Montalto delle Marche_feed.xml",
    "scraper": "https://github.com/ebergam/halley2RSS",
    "maintainer": "Enrico Bergamini <enrico.bergamini@ondata.it> (http://www.enricobergamini.it/)"
  },
  {
    "id": "c_f428_a",
    "title": "Albo Pretorio del Comune di Montappone",
    "description": "*non ufficiale* RSS feed dell'Albo Pretorio di Montappone",
    "administration": "Comune di Montappone",
    "ipa_code": "c_f428",
    "istat_code": "44033",
    "url": "http://www.halleyweb.com/c044033/mc/mc_gridev_messi_datigrid.php?x=&tmphdata=1472496974183&combo1=9999",
    "feed": "http://feeds.ricostruzionetrasparente.it/albi_pretori/Montappone_feed.xml",
    "scraper": "https://github.com/ebergam/halley2RSS",
    "maintainer": "Enrico Bergamini <enrico.bergamini@ondata.it> (http://www.enricobergamini.it/)"
  },
  {
    "id": "c_f460_a",
    "title": "Albo Pretorio del Comune di Monte Cavallo",
    "description": "*non ufficiale* RSS feed dell'Albo Pretorio di Monte Cavallo",
    "administration": "Comune di Monte Cavallo",
    "ipa_code": "c_f460",
    "istat_code": "43027",
    "url": "http://www.halleyweb.com/c043027/mc/mc_gridev_messi_datigrid.php?x=&tmphdata=1472496974183&combo1=9999",
    "feed": "http://feeds.ricostruzionetrasparente.it/albi_pretori/Monte Cavallo_feed.xml",
    "scraper": "https://github.com/ebergam/halley2RSS",
    "maintainer": "Enrico Bergamini <enrico.bergamini@ondata.it> (http://www.enricobergamini.it/)"
  },
  {
    "id": "c_f487_a",
    "title": "Albo Pretorio del Comune di Montedinove",
    "description": "*non ufficiale* RSS feed dell'Albo Pretorio di Montedinove",
    "administration": "Comune di Montedinove",
    "ipa_code": "c_f487",
    "istat_code": "44034",
    "url": "http://www.halleyweb.com/c044034/mc/mc_gridev_messi_datigrid.php?x=&tmphdata=1472496974183&combo1=9999",
    "feed": "http://feeds.ricostruzionetrasparente.it/albi_pretori/Montedinove_feed.xml",
    "scraper": "https://github.com/ebergam/halley2RSS",
    "maintainer": "Enrico Bergamini <enrico.bergamini@ondata.it> (http://www.enricobergamini.it/)"
  },
  {
    "id": "c_f493_a",
    "title": "Albo Pretorio del Comune di Montefalcone Appennino",
    "description": "*non ufficiale* RSS feed dell'Albo Pretorio di Montefalcone Appennino",
    "administration": "Comune di Montefalcone Appennino",
    "ipa_code": "c_f493",
    "istat_code": "44035",
    "url": "http://www.halleyweb.com/c044035/mc/mc_gridev_messi_datigrid.php?x=&tmphdata=1472496974183&combo1=9999",
    "feed": "http://feeds.ricostruzionetrasparente.it/albi_pretori/Montefalcone Appennino_feed.xml",
    "scraper": "https://github.com/ebergam/halley2RSS",
    "maintainer": "Enrico Bergamini <enrico.bergamini@ondata.it> (http://www.enricobergamini.it/)"
  },
  {
    "id": "c_f510_a",
    "title": "Albo Pretorio del Comune di Montefranco",
    "description": "*non ufficiale* RSS feed dell'Albo Pretorio di Montefranco",
    "administration": "Comune di Montefranco",
    "ipa_code": "c_f510",
    "istat_code": "55019",
    "url": "http://www.halleyweb.com/c055019/mc/mc_gridev_messi_datigrid.php?x=&tmphdata=1472496974183&combo1=9999",
    "feed": "http://feeds.ricostruzionetrasparente.it/albi_pretori/Montefranco_feed.xml",
    "scraper": "https://github.com/ebergam/halley2RSS",
    "maintainer": "Enrico Bergamini <enrico.bergamini@ondata.it> (http://www.enricobergamini.it/)"
  },
  {
    "id": "c_f520_a",
    "title": "Albo Pretorio del Comune di Montegiorgio",
    "description": "*non ufficiale* RSS feed dell'Albo Pretorio di Montegiorgio",
    "administration": "Comune di Montegiorgio",
    "ipa_code": "c_f520",
    "istat_code": "109017",
    "url": "http://www.halleyweb.com/c109017/mc/mc_gridev_messi_datigrid.php?x=&tmphdata=1472496974183&combo1=9999",
    "feed": "http://feeds.ricostruzionetrasparente.it/albi_pretori/Montegiorgio_feed.xml",
    "scraper": "https://github.com/ebergam/halley2RSS",
    "maintainer": "Enrico Bergamini <enrico.bergamini@ondata.it> (http://www.enricobergamini.it/)"
  },
  {
    "id": "c_f536_a",
    "title": "Albo Pretorio del Comune di Monteleone di Fermo",
    "description": "*non ufficiale* RSS feed dell'Albo Pretorio di Monteleone di Fermo",
    "administration": "Comune di Monteleone di Fermo",
    "ipa_code": "c_f536",
    "istat_code": "44042",
    "url": "http://www.halleyweb.com/c044042/mc/mc_gridev_messi_datigrid.php?x=&tmphdata=1472496974183&combo1=9999",
    "feed": "http://feeds.ricostruzionetrasparente.it/albi_pretori/Monteleone di Fermo_feed.xml",
    "scraper": "https://github.com/ebergam/halley2RSS",
    "maintainer": "Enrico Bergamini <enrico.bergamini@ondata.it> (http://www.enricobergamini.it/)"
  },
  {
    "id": "c_f549_a",
    "title": "Albo Pretorio del Comune di Montelparo",
    "description": "*non ufficiale* RSS feed dell'Albo Pretorio di Montelparo",
    "administration": "Comune di Montelparo",
    "ipa_code": "c_f549",
    "istat_code": "44043",
    "url": "http://www.halleyweb.com/c044043/mc/mc_gridev_messi_datigrid.php?x=&tmphdata=1472496974183&combo1=9999",
    "feed": "http://feeds.ricostruzionetrasparente.it/albi_pretori/Montelparo_feed.xml",
    "scraper": "https://github.com/ebergam/halley2RSS",
    "maintainer": "Enrico Bergamini <enrico.bergamini@ondata.it> (http://www.enricobergamini.it/)"
  },
  {
    "id": "c_f567_a",
    "title": "Albo Pretorio del Comune di Pollenza",
    "description": "*non ufficiale* RSS feed dell'Albo Pretorio di Pollenza",
    "administration": "Comune di Pollenza",
    "ipa_code": "c_f567",
    "istat_code": "43041",
    "url": "http://www.halleyweb.com/c043041/mc/mc_gridev_messi_datigrid.php?x=&tmphdata=1472496974183&combo1=9999",
    "feed": "http://feeds.ricostruzionetrasparente.it/albi_pretori/Pollenza_feed.xml",
    "scraper": "https://github.com/ebergam/halley2RSS",
    "maintainer": "Enrico Bergamini <enrico.bergamini@ondata.it> (http://www.enricobergamini.it/)"
  },
  {
    "id": "c_f622_a",
    "title": "Albo Pretorio del Comune di Monte San Martino",
    "description": "*non ufficiale* RSS feed dell'Albo Pretorio di Monte San Martino",
    "administration": "Comune di Monte San Martino",
    "ipa_code": "c_f622",
    "istat_code": "43032",
    "url": "http://www.halleyweb.com/c043032/mc/mc_gridev_messi_datigrid.php?x=&tmphdata=1472496974183&combo1=9999",
    "feed": "http://feeds.ricostruzionetrasparente.it/albi_pretori/Monte San Martino_feed.xml",
    "scraper": "https://github.com/ebergam/halley2RSS",
    "maintainer": "Enrico Bergamini <enrico.bergamini@ondata.it> (http://www.enricobergamini.it/)"
  },
  {
    "id": "c_f665_a",
    "title": "Albo Pretorio del Comune di Monte Vidon Corrado",
    "description": "*non ufficiale* RSS feed dell'Albo Pretorio di Monte Vidon Corrado",
    "administration": "Comune di Monte Vidon Corrado",
    "ipa_code": "c_f665",
    "istat_code": "44051",
    "url": "http://www.halleyweb.com/c044051/mc/mc_gridev_messi_datigrid.php?x=&tmphdata=1472496974183&combo1=9999",
    "feed": "http://feeds.ricostruzionetrasparente.it/albi_pretori/Monte Vidon Corrado_feed.xml",
    "scraper": "https://github.com/ebergam/halley2RSS",
    "maintainer": "Enrico Bergamini <enrico.bergamini@ondata.it> (http://www.enricobergamini.it/)"
  },
  {
    "id": "c_F793_a",
    "title": "Albo Pretorio del Comune di Muccia",
    "description": "*non ufficiale* RSS feed dell'Albo Pretorio di Muccia",
    "administration": "Comune di Muccia",
    "ipa_code": "c_F793",
    "istat_code": "43034",
    "url": "http://www.halleyweb.com/c043034/mc/mc_gridev_messi_datigrid.php?x=&tmphdata=1472496974183&combo1=9999",
    "feed": "http://feeds.ricostruzionetrasparente.it/albi_pretori/Muccia_feed.xml",
    "scraper": "https://github.com/ebergam/halley2RSS",
    "maintainer": "Enrico Bergamini <enrico.bergamini@ondata.it> (http://www.enricobergamini.it/)"
  },
  {
    "id": "c_g137_a",
    "title": "Albo Pretorio del Comune di Ortezzano",
    "description": "*non ufficiale* RSS feed dell'Albo Pretorio di Ortezzano",
    "administration": "Comune di Ortezzano",
    "ipa_code": "c_g137",
    "istat_code": "44055",
    "url": "http://www.halleyweb.com/c044055/mc/mc_gridev_messi_datigrid.php?x=&tmphdata=1472496974183&combo1=9999",
    "feed": "http://feeds.ricostruzionetrasparente.it/albi_pretori/Ortezzano_feed.xml",
    "scraper": "https://github.com/ebergam/halley2RSS",
    "maintainer": "Enrico Bergamini <enrico.bergamini@ondata.it> (http://www.enricobergamini.it/)"
  },
  {
    "id": "c_g289_a",
    "title": "Albo Pretorio del Comune di Palmiano",
    "description": "*non ufficiale* RSS feed dell'Albo Pretorio di Palmiano",
    "administration": "Comune di Palmiano",
    "ipa_code": "c_g289",
    "istat_code": "44056",
    "url": "http://www.halleyweb.com/c044056/mc/mc_gridev_messi_datigrid.php?x=&tmphdata=1472496974183&combo1=9999",
    "feed": "http://feeds.ricostruzionetrasparente.it/albi_pretori/Palmiano_feed.xml",
    "scraper": "https://github.com/ebergam/halley2RSS",
    "maintainer": "Enrico Bergamini <enrico.bergamini@ondata.it> (http://www.enricobergamini.it/)"
  },
  {
    "id": "c_g436_a",
    "title": "Albo Pretorio del Comune di Penna San Giovanni",
    "description": "*non ufficiale* RSS feed dell'Albo Pretorio di Penna San Giovanni",
    "administration": "Comune di Penna San Giovanni",
    "ipa_code": "c_g436",
    "istat_code": "43035",
    "url": "http://www.halleyweb.com/c043035/mc/mc_gridev_messi_datigrid.php?x=&tmphdata=1472496974183&combo1=9999",
    "feed": "http://feeds.ricostruzionetrasparente.it/albi_pretori/Penna San Giovanni_feed.xml",
    "scraper": "https://github.com/ebergam/halley2RSS",
    "maintainer": "Enrico Bergamini <enrico.bergamini@ondata.it> (http://www.enricobergamini.it/)"
  },
  {
    "id": "c_g515_a",
    "title": "Albo Pretorio del Comune di Petriolo",
    "description": "*non ufficiale* RSS feed dell'Albo Pretorio di Petriolo",
    "administration": "Comune di Petriolo",
    "ipa_code": "c_g515",
    "istat_code": "43036",
    "url": "http://www.halleyweb.com/c043036/mc/mc_gridev_messi_datigrid.php?x=&tmphdata=1472496974183&combo1=9999",
    "feed": "http://feeds.ricostruzionetrasparente.it/albi_pretori/Petriolo_feed.xml",
    "scraper": "https://github.com/ebergam/halley2RSS",
    "maintainer": "Enrico Bergamini <enrico.bergamini@ondata.it> (http://www.enricobergamini.it/)"
  },
  {
    "id": "c_g637_a",
    "title": "Albo Pretorio del Comune di Pievebovigliana",
    "description": "*non ufficiale* RSS feed dell'Albo Pretorio di Pievebovigliana",
    "administration": "Comune di Pievebovigliana",
    "ipa_code": "c_g637",
    "istat_code": "43037",
    "url": "http://www.halleyweb.com/c043037/mc/mc_gridev_messi_datigrid.php?x=&tmphdata=1472496974183&combo1=9999",
    "feed": "http://feeds.ricostruzionetrasparente.it/albi_pretori/Pievebovigliana_feed.xml",
    "scraper": "https://github.com/ebergam/halley2RSS",
    "maintainer": "Enrico Bergamini <enrico.bergamini@ondata.it> (http://www.enricobergamini.it/)"
  },
  {
    "id": "c_g657_a",
    "title": "Albo Pretorio del Comune di Pieve Torina",
    "description": "*non ufficiale* RSS feed dell'Albo Pretorio di Pieve Torina",
    "administration": "Comune di Pieve Torina",
    "ipa_code": "c_g657",
    "istat_code": "43038",
    "url": "http://www.halleyweb.com/c043038/mc/mc_gridev_messi_datigrid.php?x=&tmphdata=1472496974183&combo1=9999",
    "feed": "http://feeds.ricostruzionetrasparente.it/albi_pretori/Pieve Torina_feed.xml",
    "scraper": "https://github.com/ebergam/halley2RSS",
    "maintainer": "Enrico Bergamini <enrico.bergamini@ondata.it> (http://www.enricobergamini.it/)"
  },
  {
    "id": "c_g756_a",
    "title": "Albo Pretorio del Comune di Poggio Bustone",
    "description": "*non ufficiale* RSS feed dell'Albo Pretorio di Poggio Bustone",
    "administration": "Comune di Poggio Bustone",
    "ipa_code": "c_g756",
    "istat_code": "57051",
    "url": "http://www.halleyweb.com/c057051/mc/mc_gridev_messi_datigrid.php?x=&tmphdata=1472496974183&combo1=9999",
    "feed": "http://feeds.ricostruzionetrasparente.it/albi_pretori/Poggio Bustone_feed.xml",
    "scraper": "https://github.com/ebergam/halley2RSS",
    "maintainer": "Enrico Bergamini <enrico.bergamini@ondata.it> (http://www.enricobergamini.it/)"
  },
  {
    "id": "c_g758_a",
    "title": "Albo Pretorio del Comune di Poggiodomo",
    "description": "*non ufficiale* RSS feed dell'Albo Pretorio di Poggiodomo",
    "administration": "Comune di Poggiodomo",
    "ipa_code": "c_g758",
    "istat_code": "54042",
    "url": "http://www.halleyweb.com/c054042/mc/mc_gridev_messi_datigrid.php?x=&tmphdata=1472496974183&combo1=9999",
    "feed": "http://feeds.ricostruzionetrasparente.it/albi_pretori/Poggiodomo_feed.xml",
    "scraper": "https://github.com/ebergam/halley2RSS",
    "maintainer": "Enrico Bergamini <enrico.bergamini@ondata.it> (http://www.enricobergamini.it/)"
  },
  {
    "id": "c_g934_a",
    "title": "Albo Pretorio del Comune di Posta",
    "description": "*non ufficiale* RSS feed dell'Albo Pretorio di Posta",
    "administration": "Comune di Posta",
    "ipa_code": "c_g934",
    "istat_code": "57057",
    "url": "http://www.halleyweb.com/c057057/mc/mc_gridev_messi_datigrid.php?x=&tmphdata=1472496974183&combo1=9999",
    "feed": "http://feeds.ricostruzionetrasparente.it/albi_pretori/Posta_feed.xml",
    "scraper": "https://github.com/ebergam/halley2RSS",
    "maintainer": "Enrico Bergamini <enrico.bergamini@ondata.it> (http://www.enricobergamini.it/)"
  },
  {
    "id": "c_h323_a",
    "title": "Albo Pretorio del Comune di Ripe San Ginesio",
    "description": "*non ufficiale* RSS feed dell'Albo Pretorio di Ripe San Ginesio",
    "administration": "Comune di Ripe San Ginesio",
    "ipa_code": "c_h323",
    "istat_code": "43045",
    "url": "http://www.halleyweb.com/c043045/mc/mc_gridev_messi_datigrid.php?x=&tmphdata=1472496974183&combo1=9999",
    "feed": "http://feeds.ricostruzionetrasparente.it/albi_pretori/Ripe San Ginesio_feed.xml",
    "scraper": "https://github.com/ebergam/halley2RSS",
    "maintainer": "Enrico Bergamini <enrico.bergamini@ondata.it> (http://www.enricobergamini.it/)"
  },
  {
    "id": "c_h390_a",
    "title": "Albo Pretorio del Comune di Roccafluvione",
    "description": "*non ufficiale* RSS feed dell'Albo Pretorio di Roccafluvione",
    "administration": "Comune di Roccafluvione",
    "ipa_code": "c_h390",
    "istat_code": "44064",
    "url": "http://www.halleyweb.com/c044064/mc/mc_gridev_messi_datigrid.php?x=&tmphdata=1472496974183&combo1=9999",
    "feed": "http://feeds.ricostruzionetrasparente.it/albi_pretori/Roccafluvione_feed.xml",
    "scraper": "https://github.com/ebergam/halley2RSS",
    "maintainer": "Enrico Bergamini <enrico.bergamini@ondata.it> (http://www.enricobergamini.it/)"
  },
  {
    "id": "c_h588_a",
    "title": "Albo Pretorio del Comune di Rotella",
    "description": "*non ufficiale* RSS feed dell'Albo Pretorio di Rotella",
    "administration": "Comune di Rotella",
    "ipa_code": "c_h588",
    "istat_code": "44065",
    "url": "http://www.halleyweb.com/c044065/mc/mc_gridev_messi_datigrid.php?x=&tmphdata=1472496974183&combo1=9999",
    "feed": "http://feeds.ricostruzionetrasparente.it/albi_pretori/Rotella_feed.xml",
    "scraper": "https://github.com/ebergam/halley2RSS",
    "maintainer": "Enrico Bergamini <enrico.bergamini@ondata.it> (http://www.enricobergamini.it/)"
  },
  {
    "id": "c_h876_a",
    "title": "Albo Pretorio del Comune di San Ginesio",
    "description": "*non ufficiale* RSS feed dell'Albo Pretorio di San Ginesio",
    "administration": "Comune di San Ginesio",
    "ipa_code": "c_h876",
    "istat_code": "43046",
    "url": "http://www.halleyweb.com/c043046/mc/mc_gridev_messi_datigrid.php?x=&tmphdata=1472496974183&combo1=9999",
    "feed": "http://feeds.ricostruzionetrasparente.it/albi_pretori/San Ginesio_feed.xml",
    "scraper": "https://github.com/ebergam/halley2RSS",
    "maintainer": "Enrico Bergamini <enrico.bergamini@ondata.it> (http://www.enricobergamini.it/)"
  },
  {
    "id": "c_i158_a",
    "title": "Albo Pretorio del Comune di San Severino Marche",
    "description": "*non ufficiale* RSS feed dell'Albo Pretorio di San Severino Marche",
    "administration": "Comune di San Severino Marche",
    "ipa_code": "c_i158",
    "istat_code": "43047",
    "url": "http://www.halleyweb.com/c043047/mc/mc_gridev_messi_datigrid.php?x=&tmphdata=1472496974183&combo1=9999",
    "feed": "http://feeds.ricostruzionetrasparente.it/albi_pretori/San Severino Marche_feed.xml",
    "scraper": "https://github.com/ebergam/halley2RSS",
    "maintainer": "Enrico Bergamini <enrico.bergamini@ondata.it> (http://www.enricobergamini.it/)"
  },
  {
    "id": "c_i263_a",
    "title": "Albo Pretorio del Comune di Sant'Anatolia di Narco",
    "description": "*non ufficiale* RSS feed dell'Albo Pretorio di Sant'Anatolia di Narco",
    "administration": "Comune di Sant'Anatolia di Narco",
    "ipa_code": "c_i263",
    "istat_code": "54045",
    "url": "http://www.halleyweb.com/c054045/mc/mc_gridev_messi_datigrid.php?x=&tmphdata=1472496974183&combo1=9999",
    "feed": "http://feeds.ricostruzionetrasparente.it/albi_pretori/Sant'Anatolia di Narco_feed.xml",
    "scraper": "https://github.com/ebergam/halley2RSS",
    "maintainer": "Enrico Bergamini <enrico.bergamini@ondata.it> (http://www.enricobergamini.it/)"
  },
  {
    "id": "c_i286_a",
    "title": "Albo Pretorio del Comune di Sant'Angelo in Pontano",
    "description": "*non ufficiale* RSS feed dell'Albo Pretorio di Sant'Angelo in Pontano",
    "administration": "Comune di Sant'Angelo in Pontano",
    "ipa_code": "c_i286",
    "istat_code": "43048",
    "url": "http://www.halleyweb.com/c043048/mc/mc_gridev_messi_datigrid.php?x=&tmphdata=1472496974183&combo1=9999",
    "feed": "http://feeds.ricostruzionetrasparente.it/albi_pretori/Sant'Angelo in Pontano_feed.xml",
    "scraper": "https://github.com/ebergam/halley2RSS",
    "maintainer": "Enrico Bergamini <enrico.bergamini@ondata.it> (http://www.enricobergamini.it/)"
  },
  {
    "id": "c_i315_a",
    "title": "Albo Pretorio del Comune di Santa Vittoria in Matenano",
    "description": "*non ufficiale* RSS feed dell'Albo Pretorio di Santa Vittoria in Matenano",
    "administration": "Comune di Santa Vittoria in Matenano",
    "ipa_code": "c_i315",
    "istat_code": "44067",
    "url": "http://www.halleyweb.com/c044067/mc/mc_gridev_messi_datigrid.php?x=&tmphdata=1472496974183&combo1=9999",
    "feed": "http://feeds.ricostruzionetrasparente.it/albi_pretori/Santa Vittoria in Matenano_feed.xml",
    "scraper": "https://github.com/ebergam/halley2RSS",
    "maintainer": "Enrico Bergamini <enrico.bergamini@ondata.it> (http://www.enricobergamini.it/)"
  },
  {
    "id": "c_i585_a",
    "title": "Albo Pretorio del Comune di Sellano",
    "description": "*non ufficiale* RSS feed dell'Albo Pretorio di Sellano",
    "administration": "Comune di Sellano",
    "ipa_code": "c_i585",
    "istat_code": "54048",
    "url": "http://www.halleyweb.com/c054048/mc/mc_gridev_messi_datigrid.php?x=&tmphdata=1472496974183&combo1=9999",
    "feed": "http://feeds.ricostruzionetrasparente.it/albi_pretori/Sellano_feed.xml",
    "scraper": "https://github.com/ebergam/halley2RSS",
    "maintainer": "Enrico Bergamini <enrico.bergamini@ondata.it> (http://www.enricobergamini.it/)"
  },
  {
    "id": "c_i651_a",
    "title": "Albo Pretorio del Comune di Serrapetrona",
    "description": "*non ufficiale* RSS feed dell'Albo Pretorio di Serrapetrona",
    "administration": "Comune di Serrapetrona",
    "ipa_code": "c_i651",
    "istat_code": "43051",
    "url": "http://www.halleyweb.com/c043051/mc/mc_gridev_messi_datigrid.php?x=&tmphdata=1472496974183&combo1=9999",
    "feed": "http://feeds.ricostruzionetrasparente.it/albi_pretori/Serrapetrona_feed.xml",
    "scraper": "https://github.com/ebergam/halley2RSS",
    "maintainer": "Enrico Bergamini <enrico.bergamini@ondata.it> (http://www.enricobergamini.it/)"
  },
  {
    "id": "c_i661_a",
    "title": "Albo Pretorio del Comune di Serravalle di Chienti",
    "description": "*non ufficiale* RSS feed dell'Albo Pretorio di Serravalle di Chienti",
    "administration": "Comune di Serravalle di Chienti",
    "ipa_code": "c_i661",
    "istat_code": "43052",
    "url": "http://www.halleyweb.com/c043052/mc/mc_gridev_messi_datigrid.php?x=&tmphdata=1472496974183&combo1=9999",
    "feed": "http://feeds.ricostruzionetrasparente.it/albi_pretori/Serravalle di Chienti_feed.xml",
    "scraper": "https://github.com/ebergam/halley2RSS",
    "maintainer": "Enrico Bergamini <enrico.bergamini@ondata.it> (http://www.enricobergamini.it/)"
  },
  {
    "id": "c_i774_a",
    "title": "Albo Pretorio del Comune di Smerillo",
    "description": "*non ufficiale* RSS feed dell'Albo Pretorio di Smerillo",
    "administration": "Comune di Smerillo",
    "ipa_code": "c_i774",
    "istat_code": "109039",
    "url": "http://www.halleyweb.com/c109039/mc/mc_gridev_messi_datigrid.php?x=&tmphdata=1472496974183&combo1=9999",
    "feed": "http://feeds.ricostruzionetrasparente.it/albi_pretori/Smerillo_feed.xml",
    "scraper": "https://github.com/ebergam/halley2RSS",
    "maintainer": "Enrico Bergamini <enrico.bergamini@ondata.it> (http://www.enricobergamini.it/)"
  },
  {
    "id": "c_l295_a",
    "title": "Albo Pretorio del Comune di Torricella Sicura",
    "description": "*non ufficiale* RSS feed dell'Albo Pretorio di Torricella Sicura",
    "administration": "Comune di Torricella Sicura",
    "ipa_code": "c_l295",
    "istat_code": "67043",
    "url": "http://www.halleyweb.com/c067043/mc/mc_gridev_messi_datigrid.php?x=&tmphdata=1472496974183&combo1=9999",
    "feed": "http://feeds.ricostruzionetrasparente.it/albi_pretori/Torricella Sicura_feed.xml",
    "scraper": "https://github.com/ebergam/halley2RSS",
    "maintainer": "Enrico Bergamini <enrico.bergamini@ondata.it> (http://www.enricobergamini.it/)"
  },
  {
    "id": "c_l314_a",
    "title": "Albo Pretorio del Comune di Tossicia",
    "description": "*non ufficiale* RSS feed dell'Albo Pretorio di Tossicia",
    "administration": "Comune di Tossicia",
    "ipa_code": "c_l314",
    "istat_code": "67045",
    "url": "http://www.halleyweb.com/c067045/mc/mc_gridev_messi_datigrid.php?x=&tmphdata=1472496974183&combo1=9999",
    "feed": "http://feeds.ricostruzionetrasparente.it/albi_pretori/Tossicia_feed.xml",
    "scraper": "https://github.com/ebergam/halley2RSS",
    "maintainer": "Enrico Bergamini <enrico.bergamini@ondata.it> (http://www.enricobergamini.it/)"
  },
  {
    "id": "c_l366_a",
    "title": "Albo Pretorio del Comune di Treia",
    "description": "*non ufficiale* RSS feed dell'Albo Pretorio di Treia",
    "administration": "Comune di Treia",
    "ipa_code": "c_l366",
    "istat_code": "43054",
    "url": "http://www.halleyweb.com/c043054/mc/mc_gridev_messi_datigrid.php?x=&tmphdata=1472496974183&combo1=9999",
    "feed": "http://feeds.ricostruzionetrasparente.it/albi_pretori/Treia_feed.xml",
    "scraper": "https://github.com/ebergam/halley2RSS",
    "maintainer": "Enrico Bergamini <enrico.bergamini@ondata.it> (http://www.enricobergamini.it/)"
  },
  {
    "id": "c_l501_a",
    "title": "Albo Pretorio del Comune di Urbisaglia",
    "description": "*non ufficiale* RSS feed dell'Albo Pretorio di Urbisaglia",
    "administration": "Comune di Urbisaglia",
    "ipa_code": "c_l501",
    "istat_code": "43055",
    "url": "http://www.halleyweb.com/c043055/mc/mc_gridev_messi_datigrid.php?x=&tmphdata=1472496974183&combo1=9999",
    "feed": "http://feeds.ricostruzionetrasparente.it/albi_pretori/Urbisaglia_feed.xml",
    "scraper": "https://github.com/ebergam/halley2RSS",
    "maintainer": "Enrico Bergamini <enrico.bergamini@ondata.it> (http://www.enricobergamini.it/)"
  },
  {
    "id": "c_l517_a",
    "title": "Albo Pretorio del Comune di Ussita",
    "description": "*non ufficiale* RSS feed dell'Albo Pretorio di Ussita",
    "administration": "Comune di Ussita",
    "ipa_code": "c_l517",
    "istat_code": "43056",
    "url": "http://www.halleyweb.com/c043056/mc/mc_gridev_messi_datigrid.php?x=&tmphdata=1472496974183&combo1=9999",
    "feed": "http://feeds.ricostruzionetrasparente.it/albi_pretori/Ussita_feed.xml",
    "scraper": "https://github.com/ebergam/halley2RSS",
    "maintainer": "Enrico Bergamini <enrico.bergamini@ondata.it> (http://www.enricobergamini.it/)"
  },
  {
    "id": "c_l627_a",
    "title": "Albo Pretorio del Comune di Vallo di Nera",
    "description": "*non ufficiale* RSS feed dell'Albo Pretorio di Vallo di Nera",
    "administration": "Comune di Vallo di Nera",
    "ipa_code": "c_l627",
    "istat_code": "54058",
    "url": "http://www.halleyweb.com/c054058/mc/mc_gridev_messi_datigrid.php?x=&tmphdata=1472496974183&combo1=9999",
    "feed": "http://feeds.ricostruzionetrasparente.it/albi_pretori/Vallo di Nera_feed.xml",
    "scraper": "https://github.com/ebergam/halley2RSS",
    "maintainer": "Enrico Bergamini <enrico.bergamini@ondata.it> (http://www.enricobergamini.it/)"
  },
  {
    "id": "c_l728_a",
    "title": "Albo Pretorio del Comune di Venarotta",
    "description": "*non ufficiale* RSS feed dell'Albo Pretorio di Venarotta",
    "administration": "Comune di Venarotta",
    "ipa_code": "c_l728",
    "istat_code": "44073",
    "url": "http://www.halleyweb.com/c044073/mc/mc_gridev_messi_datigrid.php?x=&tmphdata=1472496974183&combo1=9999",
    "feed": "http://feeds.ricostruzionetrasparente.it/albi_pretori/Venarotta_feed.xml",
    "scraper": "https://github.com/ebergam/halley2RSS",
    "maintainer": "Enrico Bergamini <enrico.bergamini@ondata.it> (http://www.enricobergamini.it/)"
  },
  {
    "id": "c_m078_a",
    "title": "Albo Pretorio del Comune di Visso",
    "description": "*non ufficiale* RSS feed dell'Albo Pretorio di Visso",
    "administration": "Comune di Visso",
    "ipa_code": "c_m078",
    "istat_code": "43057",
    "url": "http://www.halleyweb.com/c043057/mc/mc_gridev_messi_datigrid.php?x=&tmphdata=1472496974183&combo1=9999",
    "feed": "http://feeds.ricostruzionetrasparente.it/albi_pretori/Visso_feed.xml",
    "scraper": "https://github.com/ebergam/halley2RSS",
    "maintainer": "Enrico Bergamini <enrico.bergamini@ondata.it> (http://www.enricobergamini.it/)"
  },
  {
    "id": "c_c524_a",
    "title": "Albo Pretorio del Comune di Cerreto D'Esi",
    "description": "*non ufficiale* RSS feed dell'Albo Pretorio di Cerreto D'Esi",
    "administration": "Comune di Cerreto d'Esi",
    "ipa_code": "c_c524",
    "istat_code": "42013",
    "url": "http://www.halleyweb.com/c042013/mc/mc_gridev_messi_datigrid.php?x=&tmphdata=1472496974183&combo1=9999",
    "feed": "http://feeds.ricostruzionetrasparente.it/albi_pretori/Cerreto D'Esi_feed.xml",
    "scraper": "https://github.com/ebergam/halley2RSS",
    "maintainer": "Enrico Bergamini <enrico.bergamini@ondata.it> (http://www.enricobergamini.it/)"
  }
]
